kappakit/__init__.py
kappakit/curvature/__init__.py
kappakit/curvature/curvature.py
kappakit/data/__init__.py
kappakit/data/diffusion/models.py
kappakit/data/real_manifolds/FMNIST.py
kappakit/data/real_manifolds/KMNIST.py
kappakit/data/real_manifolds/MNIST.py
kappakit/data/real_manifolds/StanfordBunny.py
kappakit/data/real_manifolds/__init__.py
kappakit/data/toy_manifolds/Ball.py
kappakit/data/toy_manifolds/Blob.py
kappakit/data/toy_manifolds/ColorspaceSphere.py
kappakit/data/toy_manifolds/Cylinder.py
kappakit/data/toy_manifolds/Ellipsoid.py
kappakit/data/toy_manifolds/MobiusStrip.py
kappakit/data/toy_manifolds/Paraboloid.py
kappakit/data/toy_manifolds/Roll.py
kappakit/data/toy_manifolds/S_Curve.py
kappakit/data/toy_manifolds/Sphere.py
kappakit/data/toy_manifolds/Torus.py
kappakit/data/toy_manifolds/__init__.py
kappakit/estimation/__init__.py
kappakit/estimation/diffusion_map/__init__.py
kappakit/estimation/diffusion_map/diffusion_map.py
kappakit/estimation/diffusion_model/__init__.py
kappakit/estimation/diffusion_model/architectures.py
kappakit/estimation/diffusion_model/diffusion_tools.py
kappakit/estimation/graph_ricci/__init__.py
kappakit/estimation/graph_ricci/graph_ricci_curvature.py
kappakit/estimation/interpolation/__init__.py
kappakit/estimation/interpolation/interpolations.py
kappakit/estimation/regression/__init__.py
kappakit/estimation/regression/regression.py
kappakit/plotting/__init__.py
kappakit/plotting/image_utils.py
kappakit/plotting/log_utils.py
kappakit/plotting/visualize.py
kappakit/routines/__init__.py
kappakit/routines/create_dataset.py
kappakit/routines/estimate_curvature.py
kappakit/routines/train_diffusion_model.py
kappakit/routines/upsample_with_diffusion.py
kappakit/routines/visualize_interactive.py
kappakit-0.1.0.dist-info/licenses/LICENSE.txt
kappakit-0.1.0.dist-info/METADATA
kappakit-0.1.0.dist-info/WHEEL
kappakit-0.1.0.dist-info/top_level.txt
kappakit-0.1.0.dist-info/RECORD
