Metadata-Version: 2.4
Name: kappakit
Version: 0.1.0
Summary: Estimating the curvature of a manifold from data
Author: Jason Wang, Bobak Kiani, Melanie Weber
License: MIT License
Project-URL: Homepage, https://github.com/Weber-GeoML/kappakit
Project-URL: Documentation, https://kappakit.readthedocs.io/en/latest/
Project-URL: Repository, https://github.com/Weber-GeoML/kappakit
Keywords: curvature,manifold,differential geometry,second fundamental form
Classifier: Programming Language :: Python
Requires-Python: >=3.10
License-File: LICENSE.txt
Requires-Dist: jsonargparse>=4.35.0
Requires-Dist: jaxtyping>=0.2.36
Requires-Dist: wandb>=0.18.6
Requires-Dist: numpy>=1.25.2
Requires-Dist: scipy>=1.9.3
Requires-Dist: pandas>=2.2.1
Requires-Dist: scikit-learn>=1.4.1
Requires-Dist: torch>=2.2.0
Requires-Dist: pymanopt>=2.2.0
Requires-Dist: GraphRicciCurvature>=0.5.3.2
Requires-Dist: huggingface-hub>=0.22.1
Requires-Dist: transformers>=4.40.0
Requires-Dist: accelerate>=0.28.0
Requires-Dist: datasets>=2.18.0
Requires-Dist: diffusers>=0.27.2
Requires-Dist: matplotlib>=3.8.3
Requires-Dist: kaleido>=0.2.1
Requires-Dist: plotly>=5.20.0
Requires-Dist: dash>=2.18.2
Requires-Dist: pygwalker>=0.4.7
Requires-Dist: kneed>=0.8.5
Dynamic: license-file
